fraee/__init__.py
fraee/main.py
fraee-0.1.0.dist-info/METADATA
fraee-0.1.0.dist-info/WHEEL
fraee-0.1.0.dist-info/top_level.txt
fraee-0.1.0.dist-info/RECORD
