Metadata-Version: 2.1
Name: fraee
Version: 0.1.0
Summary: A simple package
Home-page: https://github.com/BottleOfSugar/Fraee
Author: Franek S
Author-email: franekmeme@gmail.com
Classifier: Development Status :: 3 - Alpha
Classifier: Intended Audience :: Developers
Classifier: License :: OSI Approved :: MIT License
Classifier: Programming Language :: Python :: 3
Classifier: Programming Language :: Python :: 3.8
Classifier: Programming Language :: Python :: 3.9
Classifier: Programming Language :: Python :: 3.10
Requires-Python: >=3.12
Requires-Dist: requests
Requires-Dist: colorama
Requires-Dist: psuntil
Provides-Extra: dev
Requires-Dist: pytest ; extra == 'dev'
Requires-Dist: sphinx ; extra == 'dev'
